{"errors":[],"warnings":[],"namedChunkGroups":{"polyfill":{"chunks":[2,0,7],"assets":["webpack-runtime-5ea2c5ce7a7d114cf40c.js","webpack-runtime-5ea2c5ce7a7d114cf40c.js.map","commons-b60d2411d4e195af160f.js","commons-b60d2411d4e195af160f.js.map","polyfill-5acc46d2c6294ee52fa0.js","polyfill-5acc46d2c6294ee52fa0.js.map"],"children":{},"childAssets":{}},"app":{"chunks":[2,6,0,3],"assets":["webpack-runtime-5ea2c5ce7a7d114cf40c.js","webpack-runtime-5ea2c5ce7a7d114cf40c.js.map","framework-d585a04b7d285a7760d6.js","framework-d585a04b7d285a7760d6.js.map","commons-b60d2411d4e195af160f.js","commons-b60d2411d4e195af160f.js.map","app-12c9e0e88999563b9b2b.js","app-12c9e0e88999563b9b2b.js.map"],"children":{},"childAssets":{}},"component---src-pages-404-js":{"chunks":[1,0,4],"assets":["styles.0744685fd14862ad2a1e.css","styles-e9d24b1846c7d6eb9685.js","styles-e9d24b1846c7d6eb9685.js.map","commons-b60d2411d4e195af160f.js","commons-b60d2411d4e195af160f.js.map","component---src-pages-404-js-9c04155390b493ad90ef.js","component---src-pages-404-js-9c04155390b493ad90ef.js.map"],"children":{},"childAssets":{}},"component---src-pages-index-js":{"chunks":[1,0,5],"assets":["styles.0744685fd14862ad2a1e.css","styles-e9d24b1846c7d6eb9685.js","styles-e9d24b1846c7d6eb9685.js.map","commons-b60d2411d4e195af160f.js","commons-b60d2411d4e195af160f.js.map","component---src-pages-index-js-9f5f2c1aaddff8601d2d.js","component---src-pages-index-js-9f5f2c1aaddff8601d2d.js.map"],"children":{},"childAssets":{}}},"assetsByChunkName":{"polyfill":["webpack-runtime-5ea2c5ce7a7d114cf40c.js","commons-b60d2411d4e195af160f.js","polyfill-5acc46d2c6294ee52fa0.js"],"app":["webpack-runtime-5ea2c5ce7a7d114cf40c.js","framework-d585a04b7d285a7760d6.js","commons-b60d2411d4e195af160f.js","app-12c9e0e88999563b9b2b.js"],"component---src-pages-404-js":["styles.0744685fd14862ad2a1e.css","styles-e9d24b1846c7d6eb9685.js","commons-b60d2411d4e195af160f.js","component---src-pages-404-js-9c04155390b493ad90ef.js"],"component---src-pages-index-js":["styles.0744685fd14862ad2a1e.css","styles-e9d24b1846c7d6eb9685.js","commons-b60d2411d4e195af160f.js","component---src-pages-index-js-9f5f2c1aaddff8601d2d.js"]}}